inter_jamisson/__about__.py
inter_jamisson/__init__.py
inter_jamisson/__main__.py
inter_jamisson/main.py
inter_jamisson/cli/__init__.py
inter_jamisson/cli/template.py
inter_jamisson/cli/template/cookiecutter.json
inter_jamisson/cli/template/{{cookiecutter.nome_do_projeto}}/Dockerfile
inter_jamisson/cli/template/{{cookiecutter.nome_do_projeto}}/Makefile
inter_jamisson/cli/template/{{cookiecutter.nome_do_projeto}}/requirements.txt
inter_jamisson/cli/template/{{cookiecutter.nome_do_projeto}}/data/.gitkeep
inter_jamisson/cli/template/{{cookiecutter.nome_do_projeto}}/src/deploy.py
inter_jamisson/cli/template/{{cookiecutter.nome_do_projeto}}/src/training.py
inter_jamisson/entities/__init__.py
inter_jamisson/entities/iris_data.py
inter_jamisson/framework/__init__.py
inter_jamisson/framework/iris_model.py
inter_jamisson/interface_adapters/__init__.py
inter_jamisson/interface_adapters/data/__init__.py
inter_jamisson/interface_adapters/data/data_csv.py
inter_jamisson/interface_adapters/data/data_sklearn.py
inter_jamisson/interface_adapters/model/__init__.py
inter_jamisson/interface_adapters/model/knn_model.py
inter_jamisson/interface_adapters/model/logistic_regression.py
inter_jamisson/interface_adapters/model/random_forest_model.py
inter_jamisson/use_cases/__init__.py
inter_jamisson/use_cases/base.py
inter_jamisson/use_cases/evaluate_model.py
inter_jamisson/use_cases/save_model.py
inter_jamisson/use_cases/train_model.py
inter_jamisson/use_cases/port/data.py
inter_jamisson/use_cases/port/model.py
inter_jamisson-0.1.5.dist-info/METADATA
inter_jamisson-0.1.5.dist-info/WHEEL
inter_jamisson-0.1.5.dist-info/entry_points.txt
inter_jamisson-0.1.5.dist-info/licenses/LICENSE.txt
inter_jamisson-0.1.5.dist-info/RECORD
