Metadata-Version: 2.1
Name: inter-jamisson
Version: 0.1.5
Project-URL: Documentation, https://github.com/unknown/inter-jamisson#readme
Project-URL: Issues, https://github.com/unknown/inter-jamisson/issues
Project-URL: Source, https://github.com/unknown/inter-jamisson
Author-email: jjader <jamisson.junior@a3data.com.br>
License-Expression: MIT
License-File: LICENSE.txt
Classifier: Development Status :: 4 - Beta
Classifier: Programming Language :: Python
Classifier: Programming Language :: Python :: 3.8
Classifier: Programming Language :: Python :: 3.9
Classifier: Programming Language :: Python :: 3.10
Classifier: Programming Language :: Python :: 3.11
Classifier: Programming Language :: Python :: 3.12
Classifier: Programming Language :: Python :: Implementation :: CPython
Classifier: Programming Language :: Python :: Implementation :: PyPy
Requires-Python: >=3.8
Requires-Dist: click
Requires-Dist: cookiecutter==2.2.3
Requires-Dist: pandas==2.0.3
Requires-Dist: scikit-learn==1.3.2
